[
  {
    "author": "asdf1256",
    "href": "/bbs/Baseball/M.1575446058.A.664.html",
    "push_count": 7,
    "title": "[新聞] 陷家暴醜聞後一蹶不振 明星游擊手遭小熊"
  },
  {
    "author": "thnlkj0665",
    "href": "/bbs/Baseball/M.1575446436.A.02B.html",
    "push_count": 5,
    "title": "[分享] 有原航平 加薪7500萬日圓"
  },
  {
    "author": "Intelnet",
    "href": "/bbs/Baseball/M.1575446478.A.132.html",
    "push_count": 1,
    "title": "[新聞] 金廣鉉跨海挑戰 柳賢振提醒兩大重點"
  },
  {
    "author": "johnnyckvs",
    "href": "/bbs/Baseball/M.1575430946.A.44A.html",
    "push_count": 14,
    "title": "[先發] 2019冬盟 #29 味全龍VS韓職聯隊 @ 洲際"
  },
  {
    "author": "Intelnet",
    "href": "/bbs/Baseball/M.1575437698.A.A5E.html",
    "push_count": 23,
    "title": "[新聞] WZH-林威助、阿部慎之助同期生再會 感嘆選"
  },
  {
    "author": "iversonya",
    "href": "/bbs/Baseball/M.1575438343.A.E73.html",
    "push_count": 5,
    "title": "Re: [新聞] 奧運資格賽棒協與職棒聯盟忙搶錢 體育署"
  },
  {
    "author": "assnccu8787",
    "href": "/bbs/Baseball/M.1575438647.A.F6E.html",
    "push_count": 4,
    "title": "[問題]洋將制度改了 那味全第一年的洋將數會變嗎"
  },
  {
    "author": "SbHunt",
    "href": "/bbs/Baseball/M.1575440445.A.AE9.html",
    "push_count": 5,
    "title": "[閒聊] 金子侑司簽下四年複數年約"
  },
  {
    "author": "zzzzz843",
    "href": "/bbs/Baseball/M.1575440590.A.9D2.html",
    "push_count": 3,
    "title": "Re: [新聞] 無縫接軌樂天 翁瑋均赴日秋訓10天"
  },
  {
    "author": "Intelnet",
    "href": "/bbs/Baseball/M.1575440842.A.889.html",
    "push_count": 17,
    "title": "[新聞] 再2公里其實很難  翁瑋均自費拚了"
  },
  {
    "author": "polanco",
    "href": "/bbs/Baseball/M.1575440994.A.B18.html",
    "push_count": 12,
    "title": "[新聞] 最後一次挑戰大聯盟　金廣鉉不考慮小聯盟合約"
  },
  {
    "author": "a90575",
    "href": "/bbs/Baseball/M.1575441051.A.32A.html",
    "push_count": 5,
    "title": "[新聞] 解決6搶1紛爭　棒協應依協議精神委由中"
  },
  {
    "author": "liutj5800",
    "href": "/bbs/Baseball/M.1575441459.A.F31.html",
    "push_count": 5,
    "title": "[閒聊] 同意中職32年例行賽改回打100場嗎？"
  },
  {
    "author": "DDinin",
    "href": "/bbs/Baseball/M.1575442053.A.9D0.html",
    "push_count": 11,
    "title": "[新聞] 啦啦隊新女神歐洲行 孟潔「下身失蹤」解放！"
  },
  {
    "author": "alex8725",
    "href": "/bbs/Baseball/M.1575442363.A.660.html",
    "push_count": 0,
    "title": "Re: [專欄] 義大選秀差、富邦養成弱 球隊怎會不失敗"
  },
  {
    "author": "dahanjian",
    "href": "/bbs/Baseball/M.1575442495.A.12F.html",
    "push_count": 0,
    "title": "Re: [新聞] 奧運資格賽棒協與職棒聯盟忙搶錢 體育署"
  },
  {
    "author": "jackypan1989",
    "href": "/bbs/Baseball/M.1575443207.A.DCE.html",
    "push_count": 4,
    "title": "Re: [專欄] 義大選秀差、富邦養成弱 球隊怎會不失敗"
  },
  {
    "author": "girlwe",
    "href": "/bbs/Baseball/M.1575443363.A.8C3.html",
    "push_count": 9,
    "title": "[閒聊] 臺灣的球風似乎能剋制韓國？！"
  },
  {
    "author": "golover",
    "href": "/bbs/Baseball/M.1575443818.A.C54.html",
    "push_count": 13,
    "title": "[新聞] 阿部慎之助挖到石油 斷言黑田響生比坂本"
  },
  {
    "author": "oftisa",
    "href": "/bbs/Baseball/M.1575443962.A.8EB.html",
    "push_count": 0,
    "title": "[討論] 北海道 Ballpark將成為亞洲最好的球場？"
  },
  {
    "author": "mongi",
    "href": "/bbs/Baseball/M.1575444013.A.9A1.html",
    "push_count": 52,
    "title": "[新聞] 中職爭比賽權 台灣犬開球了"
  },
  {
    "author": "Allen524",
    "href": "/bbs/Baseball/M.1575444066.A.B0B.html",
    "push_count": 7,
    "title": "Re: [問題]洋將制度改了 那味全第一年的洋將數會變嗎"
  },
  {
    "author": "Allen524",
    "href": "/bbs/Baseball/M.1575445675.A.6FA.html",
    "push_count": 4,
    "title": "Re: [專欄] 義大選秀差、富邦養成弱 球隊怎會不失敗"
  },
  {
    "author": "JAL96",
    "href": "/bbs/Baseball/M.1575445859.A.120.html",
    "push_count": 4,
    "title": "[新聞] SPC-日職》1打點要三千萬！巨人老將降薪1"
  },
  {
    "author": "www90173",
    "href": "/bbs/Baseball/M.1575427173.A.FB9.html",
    "push_count": 19,
    "title": "Re: [專欄] 義大選秀差、富邦養成弱 球隊怎會不"
  },
  {
    "author": "mongi",
    "href": "/bbs/Baseball/M.1575427211.A.5B6.html",
    "push_count": 7,
    "title": "[新聞] spc 運動家2.2億簽回狄克曼 牛棚爭奪戰"
  },
  {
    "author": "SbHunt",
    "href": "/bbs/Baseball/M.1575427985.A.EA6.html",
    "push_count": 29,
    "title": "[分享] 山崎康晃Twitter "
  },
  {
    "author": "currykukuo",
    "href": "/bbs/Baseball/M.1575430240.A.482.html",
    "push_count": 87,
    "title": "[新聞] 小熊侵略性交易　出清3大主力「老大」、"
  },
  {
    "author": "Ayanami5566",
    "href": "/bbs/Baseball/M.1575430476.A.91F.html",
    "push_count": 27,
    "title": "[閒聊] 台灣有哪首應援曲紅到國外嗎?"
  },
  {
    "author": "currykukuo",
    "href": "/bbs/Baseball/M.1575430728.A.69D.html",
    "push_count": 0,
    "title": "[新聞] 進度比柯爾、小史快 惠勒獲一億美元報價"
  },
  {
    "author": "hunterneon",
    "href": "/bbs/Baseball/M.1575430820.A.844.html",
    "push_count": 19,
    "title": "[新聞] 有原航平表達明年球季後想去大聯盟"
  },
  {
    "author": "kindaichi21",
    "href": "/bbs/Baseball/M.1575430861.A.C5C.html",
    "push_count": 1,
    "title": "[閒聊] 有原航平談薪: 想入札打MLB"
  },
  {
    "author": "johnnyckvs",
    "href": "/bbs/Baseball/M.1575430946.A.44A.html",
    "push_count": 9,
    "title": "[先發] 2019冬盟 #29 味全龍VS韓職聯隊 @ 洲際"
  },
  {
    "author": "SbHunt",
    "href": "/bbs/Baseball/M.1575430955.A.AEA.html",
    "push_count": 5,
    "title": "[閒聊] 有原航平來年將成為億元男"
  },
  {
    "author": "hvariables",
    "href": "/bbs/Baseball/M.1575431734.A.0BB.html",
    "push_count": 60,
    "title": "[新聞] 陽岱鋼正面看待酸民 「會看你才會在意」"
  },
  {
    "author": "anzepam",
    "href": "/bbs/Baseball/M.1575432252.A.E9D.html",
    "push_count": 36,
    "title": "[專欄] 跟你玩真的！一朗投入草野球的動機與願景"
  },
  {
    "author": "nice99",
    "href": "/bbs/Baseball/M.1575433111.A.98F.html",
    "push_count": 6,
    "title": "Re: [專欄] 義大選秀差、富邦養成弱 球隊怎會不失敗"
  },
  {
    "author": "if2",
    "href": "/bbs/Baseball/M.1575433593.A.A6F.html",
    "push_count": 6,
    "title": "[新聞] 到洋基如何專注？ 基特要沙胖別看ESPN"
  },
  {
    "author": "murray",
    "href": "/bbs/Baseball/M.1575433617.A.0D4.html",
    "push_count": 80,
    "title": "[新聞] 球速只剩130　林政賢努力找方法"
  },
  {
    "author": "golover",
    "href": "/bbs/Baseball/M.1575434091.A.53C.html",
    "push_count": 3,
    "title": "[新聞] 羅華韋到味全龍報到 笑稱突然變老了"
  },
  {
    "author": "acwz7362",
    "href": "/bbs/Baseball/M.1575434541.A.A27.html",
    "push_count": 26,
    "title": "[新聞] 味全龍給測試機會 林政賢還沒有放棄"
  },
  {
    "author": "mongi",
    "href": "/bbs/Baseball/M.1575435153.A.CAF.html",
    "push_count": 53,
    "title": "[新聞] 奧運資格賽棒協與職棒聯盟忙搶錢 體育署"
  },
  {
    "author": "currykukuo",
    "href": "/bbs/Baseball/M.1575436036.A.B8A.html",
    "push_count": 36,
    "title": "[閒聊] 日本火腿認真砸錢玩會發生什麼事?"
  },
  {
    "author": "thnlkj0665",
    "href": "/bbs/Baseball/M.1575437168.A.F0C.html",
    "push_count": 16,
    "title": "[分享] 松坂大輔 與西武隊簽下一年3000萬合約"
  },
  {
    "author": "chan123",
    "href": "/bbs/Baseball/M.1575410739.A.F36.html",
    "push_count": 12,
    "title": "[新聞] 無縫接軌樂天 翁瑋均赴日秋訓10天"
  },
  {
    "author": "shiaubai",
    "href": "/bbs/Baseball/M.1575412795.A.78C.html",
    "push_count": 6,
    "title": "[新聞] 魏碩成補考好投 助總點頭"
  },
  {
    "author": "wwf0322",
    "href": "/bbs/Baseball/M.1575415882.A.20E.html",
    "push_count": 5,
    "title": "[新聞] 青棒球員力量越來越強 陽岱鋼連7年指導"
  },
  {
    "author": "polanco",
    "href": "/bbs/Baseball/M.1575416130.A.CDB.html",
    "push_count": 24,
    "title": "[新聞] 劉致榮的秘密基地 「黑山羊」完整揭密  "
  },
  {
    "author": "polanco",
    "href": "/bbs/Baseball/M.1575416426.A.D69.html",
    "push_count": 52,
    "title": "[專欄] 義大選秀差、富邦養成弱 球隊怎會不失敗"
  },
  {
    "author": "Ulysses",
    "href": "/bbs/Baseball/M.1575417431.A.B57.html",
    "push_count": 48,
    "title": "[閒聊] 巴倫汀將可能加入軟銀"
  },
  {
    "author": "lintzu83",
    "href": "/bbs/Baseball/M.1575419078.A.786.html",
    "push_count": 11,
    "title": "[閒聊] 裁判回歸球員身分的例子"
  },
  {
    "author": "CTBgu",
    "href": "/bbs/Baseball/M.1575419371.A.29C.html",
    "push_count": 10,
    "title": "Re: [閒聊] 林克謙算可惜嗎？"
  },
  {
    "author": "leonjapan",
    "href": "/bbs/Baseball/M.1575421088.A.242.html",
    "push_count": 18,
    "title": "[新聞] 苦勞功勞榜上有名 宋家豪薪水翻兩倍  "
  },
  {
    "author": "polanco",
    "href": "/bbs/Baseball/M.1575421906.A.24A.html",
    "push_count": 0,
    "title": "[分享] [WIT] 劉致榮會從二A展開職棒生涯，你相"
  },
  {
    "author": "VVizZ",
    "href": "/bbs/Baseball/M.1575422383.A.0A6.html",
    "push_count": 2,
    "title": "Re: [閒聊] 裁判回歸球員身分的例子"
  },
  {
    "author": "currykukuo",
    "href": "/bbs/Baseball/M.1575422548.A.A68.html",
    "push_count": 6,
    "title": "[新聞] 不計禁藥前嫌 曼尼和歐提茲攜手進紅襪名"
  },
  {
    "author": "currykukuo",
    "href": "/bbs/Baseball/M.1575422881.A.D1F.html",
    "push_count": 5,
    "title": "[新聞] 經國際大賽淬鍊 陳柏毓「美」夢近了"
  },
  {
    "author": "strellson",
    "href": "/bbs/Baseball/M.1575423444.A.54E.html",
    "push_count": 12,
    "title": "[新聞] MLB／兩個都想要？ 洋基先見柯爾再約小史"
  },
  {
    "author": "currykukuo",
    "href": "/bbs/Baseball/M.1575423942.A.4DC.html",
    "push_count": 13,
    "title": "[新聞] MLB／太Chill！名將雨刷伯高齡51歲　叼"
  },
  {
    "author": "ssh012314",
    "href": "/bbs/Baseball/M.1575424121.A.694.html",
    "push_count": 15,
    "title": "[新聞] 還好劉致榮選紅襪 林子偉不再孤單"
  },
  {
    "author": "barry610171",
    "href": "/bbs/Baseball/M.1575424396.A.051.html",
    "push_count": 34,
    "title": "[新聞] 職棒釋出年輕球員「很現實的環境」　郭"
  },
  {
    "author": "kindaichi21",
    "href": "/bbs/Baseball/M.1575424987.A.6F2.html",
    "push_count": 20,
    "title": "[新聞] 寫下賽揚獎、165公里 劉致榮霸氣外顯"
  },
  {
    "author": "assnccu8787",
    "href": "/bbs/Baseball/M.1575425250.A.B56.html",
    "push_count": 2,
    "title": "[問題] 吳俊杰現在是被丟到牛棚了嗎"
  },
  {
    "author": "polanco",
    "href": "/bbs/Baseball/M.1575425301.A.62D.html",
    "push_count": 21,
    "title": "[新聞] SPC洋基「All in」柯爾！ 名記者爆料："
  },
  {
    "author": "rpg1510",
    "href": "/bbs/Baseball/M.1575389734.A.B7F.html",
    "push_count": 41,
    "title": "Re: [新聞] 12強實際可穿台灣犬球衣？中職與棒協協"
  },
  {
    "author": "pttpepe",
    "href": "/bbs/Baseball/M.1575390962.A.048.html",
    "push_count": -10,
    "title": "[新聞] 中職與棒協爭辦6搶1紛爭　來龍去脈過程一"
  },
  {
    "author": "barry610171",
    "href": "/bbs/Baseball/M.1575401268.A.128.html",
    "push_count": 6,
    "title": "[新聞] 平鎮野手蹲三年　何逸龍大學初登板就奪"
  },
  {
    "author": "BBOYstyle10",
    "href": "/bbs/Baseball/M.1575404555.A.AA3.html",
    "push_count": 1,
    "title": "Re: [討論] 為何中職球員的薪水不公開?"
  },
  {
    "author": "barry610171",
    "href": "/bbs/Baseball/M.1575404590.A.645.html",
    "push_count": 5,
    "title": "[新聞] ０分到及格　魏碩成：不想要讓期望我的人"
  }
]